{"cameraMode":{"drawMode":0,"name":"Shaded","section":"Shading Mode"},"sceneLighting":true,"audioPlay":false,"sceneViewState":{"m_AlwaysRefresh":false,"showFog":true,"showSkybox":true,"showFlares":true,"showImageEffects":true,"showParticleSystems":true,"showVisualEffectGraphs":true,"m_FxEnabled":true},"in2DMode":false,"pivot":{"x":120.23681640625,"y":-40.263065338134769,"z":140.68502807617188},"rotation":{"x":0.1152508482336998,"y":0.0662519782781601,"z":-0.009281338192522526,"w":0.9916167259216309},"size":92.76699829101563,"orthographic":false}